itcpr/__init__.py
itcpr/api.py
itcpr/auth.py
itcpr/cli.py
itcpr/config.py
itcpr/gitops.py
itcpr/service.py
itcpr/storage.py
itcpr/sync.py
itcpr/utils.py
itcpr-2.1.10.dist-info/licenses/LICENSE
itcpr-2.1.10.dist-info/METADATA
itcpr-2.1.10.dist-info/WHEEL
itcpr-2.1.10.dist-info/entry_points.txt
itcpr-2.1.10.dist-info/top_level.txt
itcpr-2.1.10.dist-info/RECORD
