Metadata-Version: 2.4
Name: itcpr
Version: 2.1.10
Summary: CLI tool for syncing GitHub repositories from ITCPR Cloud
Home-page: https://itcpr.org
Author: ITCPR
Author-email: ITCPR <info@itcpr.org>
License: MIT
Keywords: itcpr,github,git,sync,cli,repository
Classifier: Development Status :: 3 - Alpha
Classifier: Intended Audience :: Developers
Classifier: License :: OSI Approved :: MIT License
Classifier: Programming Language :: Python :: 3
Classifier: Programming Language :: Python :: 3.10
Classifier: Programming Language :: Python :: 3.11
Classifier: Programming Language :: Python :: 3.12
Requires-Python: >=3.10
License-File: LICENSE
Requires-Dist: click>=8.0.0
Requires-Dist: requests>=2.28.0
Requires-Dist: keyring>=23.0.0
Requires-Dist: tomli-w>=1.0.0
Requires-Dist: PyYAML>=6.0
Provides-Extra: dev
Requires-Dist: pytest; extra == "dev"
Requires-Dist: black; extra == "dev"
Requires-Dist: flake8; extra == "dev"
Dynamic: author
Dynamic: home-page
Dynamic: license-file
Dynamic: requires-python
